Simple_neuron/relu.v
module relu(
    input [22:0] data_in,      // Input data (signed)
    output [22:0] data_out     // Output data after ReLU
);
    // ReLU function: f(x) = max(0, x)
    assign data_out = (data_in[22]) ? 22'd0 : data_in;
    // If the MSB (sign bit) is 1 (negative), output 0
    // Otherwise, pass the input value as is

endmodule

Simple_neuron/fp_sum.v
`timescale 1ns / 1ps

module fp_sum(
    input wire [22:0] num1,
    input wire [22:0] num2,
    output wire [22:0] result,
    input wire [3:0] counter
);
    // wire [22:0] signed_num1 = num1;
    // wire [22:0] signed_num2 = num2;
    reg sign;
    reg [21:0] signed_result;  // Changed to reg for use in always block

    // Procedural blocks must be in always blocks, not raw if statements
    always @(*) begin
        
      
            if (num1[22] == num2[22]) begin
                signed_result = $signed(num1) + $signed(num2);
                sign = num1[22];
            end
            else if (num2[21:0] >= num1[21:0]) begin
                signed_result = $signed(num2) - $signed(num1);
                sign = num2[22];
            end
            else begin
                signed_result = $signed(num1) - $signed(num2);
                sign = num1[22];
            end
        end
    

    assign result = {sign, signed_result};

endmodule

binary_fraction_multiplier.v
module binary_fraction_multiplier (
    input wire [11:0] num1,        // 1-sign, 2-int, 9-fraction
    input wire [11:0] num2,        // 1-sign, 9-int, 2-fraction
    output wire [22:0] result      // 1-sign, 11-int, 11-fraction
);

    // Extract sign bits
    wire sign1 = num1[11];
    wire sign2 = num2[11];
    
    // Result sign (XOR of input signs)
    wire result_sign = sign1 ^ sign2;
    
    // Extract unsigned parts of numbers
    wire [1:0] int1 = num1[10:9];
    wire [8:0] frac1 = num1[8:0];
    
    wire [8:0] int2 = num2[10:2];
    wire [1:0] frac2 = num2[1:0];
    
    // Combine integer and fractional parts for full multiplication
    wire [10:0] unsigned_val1 = {int1, frac1};  // 2-bit int + 9-bit frac = 11 bits
    wire [10:0] unsigned_val2 = {int2, frac2};  // 9-bit int + 2-bit frac = 11 bits
    
    // Perform multiplication (result will be 22 bits)
    wire [21:0] product = unsigned_val1 * unsigned_val2;
    
    // The decimal point in the result will be positioned after 11 bits from right
    // For num1: Decimal point after 9 bits from right
    // For num2: Decimal point after 2 bits from right
    // For product: Decimal point after (9+2=11) bits from right
    
    // Combine final result: sign + product
    assign result = {result_sign, product};

endmodule

nueron.v
`include "binary_fraction_multiplier.v"
`include "fp_sum.v"
`include "relu.v"

module nueron(  // Fixed module name from "nueron" to "neuron"
    input [11:0] in_data, 
    input clk, rst,
    output reg [22:0] out_data 
);
    
    reg [11:0] weight_in[2:0];
    reg [22:0] bias_in[0:0];
    reg [3:0] counter;
    reg [22:0] mult;
    wire [22:0] result;
    wire [22:0] out;
    reg [22:0] sum;
    wire [22:0] add_result;
    reg [22:0] num1;
    reg [22:0] num2;   

    binary_fraction_multiplier mut (
        .num1(in_data),
        .num2(weight_in[counter]),
        .result(result)
    );

    fp_sum sut(
        .num1(num1),
        .num2(num2),
        .result(add_result),
        .counter(counter)
    );

    relu rut(
        .data_in(add_result),
        .data_out(out)
    );
    
    initial begin
        $readmemb("w_1_0.mif", weight_in);
        $readmemb("b_1_0.mif", bias_in);
        // $display("%b", weight_in[0]);    
        // $display("%b", bias_in[0]);
    end

    // Fix: Counter logic and multiplier result handling
    always @(posedge clk) begin
        if (rst|counter >=4) begin  
            counter <= 3'b0;           
            mult <= bias_in[0];
            num1<=23'b0;
            num2<=23'b0;
            out_data<=23'b0;
            
        end
        else begin
            if(counter >=4)begin
                counter <= 3'b0;           
                mult <= bias_in[0];
                num1<=23'b0;
                num2<=23'b0;
            end

            else begin
                mult <= result;
                counter <= counter+1;
            end
        end
        
        // $display(" at counter = %b \n mult %b\n", counter, mult);
    end
    
    // // Fix: Sum accumulation logic
    always @(posedge ~clk) begin
        if (rst) begin 
            
            num1 <= 23'b0;
            num2 <= 23'b0;
        end

        else begin
            num1 <= mult;     // Current multiplication result
            num2 <= add_result;      // Current accumulated sum            
        end 
        // $display(" at counter = %b \n add result %b of num1= %b, num2 = %b\n", counter, add_result, num1, num2);
    end

    always @(posedge ~clk) begin
        if (counter>=4)begin
            out_data <= out;
            $display("%b output by relu",out); //00000110111111111010110
        end
    end

endmodule

tb_.v
`timescale 1ns / 1ps

module nueron_tb();
    // Parameters
    parameter CLK_PERIOD = 10; // Clock period in ns
    
    // Testbench signals
    reg [11:0] in_data;
    reg clk, rst;
    wire [22:0] out_data;
    
    // Instantiate the Unit Under Test (UUT)
    nueron uut (
        .in_data(in_data),
        .clk(clk),
        .rst(rst),
        .out_data(out_data)
    );
    
    // Clock generation
    initial begin
        clk = 0;
        forever #(CLK_PERIOD/2) clk = ~clk;
    end
    
    // Test stimulus
    initial begin
        // Initialize inputs
        in_data = 12'b0;
        rst = 1;
        
        // Wait for a few clock cycles
        #(CLK_PERIOD*2);
        
        // Release reset
        rst = 0;
        
        // Apply test vectors
        // Test case 1: Positive input
        in_data = 12'b101000; // 10
        #(CLK_PERIOD); // Wait 1 clock cycles
        
        // Test case 2: Negative input
        in_data = 12'b101000; // 10
        #(CLK_PERIOD);
        
        // Test case 3: Maximum positive value
        in_data = 12'b101000; // 10
        #(CLK_PERIOD);

        // $display("%b output by relu",out_data);

        // Test case 4: Maximum negative value
        in_data = 12'b1011100; // 23
        #(CLK_PERIOD);
        
        // Test case 5: Zero
        in_data = 12'b1011100; // 23
        #(CLK_PERIOD);
        // Test reset during operation
        in_data = 12'b100100001000; // -66
        #(CLK_PERIOD);
        // rst = 1;
        #(CLK_PERIOD);
        // rst = 0;
        #(CLK_PERIOD*4);
        
        // Finish simulation
        #(CLK_PERIOD*2);
        $display("Simulation completed");
        $display("%b output by relu",out_data);
        $finish;
    end
    
    // Monitor signals
    // initial begin
    //     $monitor("Time=%0t | rst=%b | in_data=%b (%d) | counter=%b | out=%b (%d) | out_data=%b",
    //              $time, rst, in_data, $signed(in_data), uut.counter, out_data);
    // end
    
    // Create VCD file for waveform viewing
    initial begin
        $dumpfile("nueron_tb.vcd");
        $dumpvars(0, nueron_tb);
    end
    
endmodule

nueron_tb.vcd
$date
	Tue Apr 15 15:50:26 2025
$end
$version
	Icarus Verilog
$end
$timescale
	1ps
$end
$scope module nueron_tb $end
$var wire 23 ! out_data [22:0] $end
$var reg 1 " clk $end
$var reg 12 # in_data [11:0] $end
$var reg 1 $ rst $end
$scope module uut $end
$var wire 23 % add_result [22:0] $end
$var wire 1 & clk $end
$var wire 12 ' in_data [11:0] $end
$var wire 23 ( out [22:0] $end
$var wire 23 ) result [22:0] $end
$var wire 1 * rst $end
$var reg 4 + counter [3:0] $end
$var reg 23 , mult [22:0] $end
$var reg 23 - num1 [22:0] $end
$var reg 23 . num2 [22:0] $end
$var reg 23 / out_data [22:0] $end
$scope module mut $end
$var wire 9 0 frac1 [8:0] $end
$var wire 2 1 frac2 [1:0] $end
$var wire 2 2 int1 [1:0] $end
$var wire 9 3 int2 [8:0] $end
$var wire 12 4 num1 [11:0] $end
$var wire 12 5 num2 [11:0] $end
$var wire 22 6 product [21:0] $end
$var wire 23 7 result [22:0] $end
$var wire 1 8 result_sign $end
$var wire 1 9 sign1 $end
$var wire 1 : sign2 $end
$var wire 11 ; unsigned_val1 [10:0] $end
$var wire 11 < unsigned_val2 [10:0] $end
$upscope $end
$scope module sut $end
$var wire 4 = counter [3:0] $end
$var wire 23 > num1 [22:0] $end
$var wire 23 ? num2 [22:0] $end
$var wire 23 @ result [22:0] $end
$var reg 1 A sign $end
$var reg 22 B signed_result [21:0] $end
$upscope $end
$scope module rut $end
$var wire 23 C data_in [22:0] $end
$var wire 23 D data_out [22:0] $end
$upscope $end
$upscope $end
$upscope $end
$enddefinitions $end
#0
$dumpvars
b0 D
b0 C
b0 B
0A
b0 @
b0 ?
b0 >
bx =
bx <
b0 ;
x:
09
x8
bx 7
bx 6
bx 5
b0 4
bx 3
b0 2
bx 1
b0 0
bx /
b0 .
b0 -
bx ,
bx +
1*
bx )
b0 (
b0 '
0&
b0 %
1$
b0 #
0"
bx !
$end
#5000
18
1:
b10000000000000000000000 )
b10000000000000000000000 7
b0 6
b101000 3
b10100000 <
b0 1
b0 /
b0 !
b10000000000000100101010 ,
b0 +
b100010100000 5
b0 =
1"
1&
#10000
0"
0&
#15000
1"
1&
#20000
b0 (
b0 D
1A
b100101010 B
b10000000000000100101010 %
b10000000000000100101010 @
b10000000000000100101010 C
b10000000000000100101010 -
b10000000000000100101010 >
b10000000011100110000000 )
b10000000011100110000000 7
b11100110000000 6
b1011100 ;
b1011100 0
0"
0&
b1011100 #
b1011100 '
b1011100 4
0$
0*
#25000
08
b11100110000000 )
b11100110000000 7
0:
b1 +
b10100000 5
b1 =
b10000000011100110000000 ,
1"
1&
#30000
b11101010101010 B
b10000000011101010101010 %
b10000000011101010101010 @
b10000000011101010101010 C
b10000000000000100101010 .
b10000000000000100101010 ?
b10000000011100110000000 -
b10000000011100110000000 >
b1000111010000000 )
b1000111010000000 7
b1000111010000000 6
b11100100 ;
b11100100 0
0"
0&
b11100100 #
b11100100 '
b11100100 4
#35000
b11001110101000000 )
b11001110101000000 7
b11001110101000000 6
b111010000 <
b1110100 3
b10 +
b111010000 5
b10 =
b1000111010000000 ,
1"
1&
#40000
b101001111010110 (
b101001111010110 D
0A
b101001111010110 B
b101001111010110 %
b101001111010110 @
b101001111010110 C
b10000000011101010101010 .
b10000000011101010101010 ?
b1000111010000000 -
b1000111010000000 >
b110010110000000000 )
b110010110000000000 7
b110010110000000000 6
b111000000 ;
b111000000 0
0"
0&
b111000000 #
b111000000 '
b111000000 4
#45000
x8
x:
bx 3
bx )
bx 7
bx 6
bx <
bx 1
b11 +
bx 5
b11 =
b110010110000000000 ,
1"
1&
#50000
b110111111111010110 (
b110111111111010110 D
b110111111111010110 B
b110111111111010110 %
b110111111111010110 @
b110111111111010110 C
b101001111010110 .
b101001111010110 ?
b110010110000000000 -
b110010110000000000 >
b1011100 ;
b1011100 0
0"
0&
b1011100 #
b1011100 '
b1011100 4
#55000
b100 +
b100 =
bx ,
1"
1&
#60000
bx (
bx D
xA
bx B
bx %
bx @
bx C
b110111111111010110 .
b110111111111010110 ?
bx -
bx >
b110111111111010110 /
b110111111111010110 !
0"
0&
#65000
18
1:
b10000000011100110000000 )
b10000000011100110000000 7
b11100110000000 6
b101000 3
b10100000 <
b0 1
b0 /
b0 !
b10000000000000100101010 ,
b0 +
b100010100000 5
b0 =
1"
1&
#70000
b0 (
b0 D
1A
b1xxxxxxxxxxxxxxxxxxxxxx %
b1xxxxxxxxxxxxxxxxxxxxxx @
b1xxxxxxxxxxxxxxxxxxxxxx C
bx .
bx ?
b10000000000000100101010 -
b10000000000000100101010 >
0"
0&
#75000
08
b11100110000000 )
b11100110000000 7
0:
b1 +
b10100000 5
b1 =
b10000000011100110000000 ,
1"
1&
#80000
b1xxxxxxxxxxxxxxxxxxxxxx .
b1xxxxxxxxxxxxxxxxxxxxxx ?
b10000000011100110000000 -
b10000000011100110000000 >
0"
0&
#85000
b1010011011000000 )
b1010011011000000 7
b1010011011000000 6
b111010000 <
b1110100 3
b10 +
b111010000 5
b10 =
b11100110000000 ,
1"
1&
#90000
b0xxxxxxxxxxxxxxxxxxxxxx (
b0xxxxxxxxxxxxxxxxxxxxxx D
0A
b0xxxxxxxxxxxxxxxxxxxxxx %
b0xxxxxxxxxxxxxxxxxxxxxx @
b0xxxxxxxxxxxxxxxxxxxxxx C
b11100110000000 -
b11100110000000 >
0"
0&
#95000
x8
x:
bx 3
bx )
bx 7
bx 6
bx <
bx 1
b11 +
bx 5
b11 =
b1010011011000000 ,
1"
1&
#100000
b0xxxxxxxxxxxxxxxxxxxxxx .
b0xxxxxxxxxxxxxxxxxxxxxx ?
b1010011011000000 -
b1010011011000000 >
0"
0&
#105000
b100 +
b100 =
bx ,
1"
1&
#110000
bx (
bx D
xA
bx %
bx @
bx C
bx -
bx >
b0xxxxxxxxxxxxxxxxxxxxxx /
b0xxxxxxxxxxxxxxxxxxxxxx !
0"
0&
#115000
18
1:
b10000000011100110000000 )
b10000000011100110000000 7
b11100110000000 6
b101000 3
b10100000 <
b0 1
b0 /
b0 !
b10000000000000100101010 ,
b0 +
b100010100000 5
b0 =
1"
1&
#120000
b0 (
b0 D
1A
b1xxxxxxxxxxxxxxxxxxxxxx %
b1xxxxxxxxxxxxxxxxxxxxxx @
b1xxxxxxxxxxxxxxxxxxxxxx C
bx .
bx ?
b10000000000000100101010 -
b10000000000000100101010 >
0"
0&
#125000
08
b11100110000000 )
b11100110000000 7
0:
b1 +
b10100000 5
b1 =
b10000000011100110000000 ,
1"
1&
#130000
b1xxxxxxxxxxxxxxxxxxxxxx .
b1xxxxxxxxxxxxxxxxxxxxxx ?
b10000000011100110000000 -
b10000000011100110000000 >
0"
0&
#135000
b1010011011000000 )
b1010011011000000 7
b1010011011000000 6
b111010000 <
b1110100 3
b10 +
b111010000 5
b10 =
b11100110000000 ,
1"
1&
#140000
b0xxxxxxxxxxxxxxxxxxxxxx (
b0xxxxxxxxxxxxxxxxxxxxxx D
0A
b0xxxxxxxxxxxxxxxxxxxxxx %
b0xxxxxxxxxxxxxxxxxxxxxx @
b0xxxxxxxxxxxxxxxxxxxxxx C
b11100110000000 -
b11100110000000 >
0"
0&
#145000
x8
x:
bx 3
bx )
bx 7
bx 6
bx <
bx 1
b11 +
bx 5
b11 =
b1010011011000000 ,
1"
1&
#150000
b0xxxxxxxxxxxxxxxxxxxxxx .
b0xxxxxxxxxxxxxxxxxxxxxx ?
b1010011011000000 -
b1010011011000000 >
0"
0&
